README.rst
setup.py
django_keyerror/__init__.py
django_keyerror/api.py
django_keyerror/app_settings.py
django_keyerror/django_lightweight_queue.py
django_keyerror/error.py
django_keyerror/middleware.py
django_keyerror/models.py
django_keyerror/utils.py
django_keyerror.egg-info/PKG-INFO
django_keyerror.egg-info/SOURCES.txt
django_keyerror.egg-info/dependency_links.txt
django_keyerror.egg-info/requires.txt
django_keyerror.egg-info/top_level.txt
django_keyerror/management/__init__.py
django_keyerror/management/commands/__init__.py
django_keyerror/management/commands/keyerror_deployment_notification.py
tests/__init__.py
tests/python_3_tests.py
tests/settings.py
tests/tests.py
tests/urls.py
tests/views.py