Metadata-Version: 1.0
Name: django-keyerror
Version: 3.7.0
Summary: KeyError.com Django client
Home-page: https://keyerror.com/docs/django
Author: Chris Lamb
Author-email: chris@keyerror.com
License: UNKNOWN
Platform: UNKNOWN
